verilog/encryptor/mla_acc.sv
module mla_accumulator #(
    parameter integer DATA_WIDTH = 12,
    // ACC_WIDTH should be large enough to hold many accumulated products.
    // For example, if the maximum product is (2^DATA_WIDTH-1)^2 then ACC_WIDTH
    // should be set wide enough (e.g. DATA_WIDTH*2 or wider) to prevent overflow.
    parameter integer ACC_WIDTH  = 32 
)(
    input  logic                             clk,
    input  logic                             rst,
    input  logic signed [2:0]     r,        // Multiplier input r.
    // Row input: packed with 4 columns.
    input  logic [(4*DATA_WIDTH)-1:0] row_in,
    input  logic [DATA_WIDTH-1:0]    sum_val,  // The additional input for the extra MLA stream.
    // Five accumulated outputs:
    output logic [ACC_WIDTH-1:0]     acc_col1,
    output logic [ACC_WIDTH-1:0]     acc_col2,
    output logic [ACC_WIDTH-1:0]     acc_col3,
    output logic [ACC_WIDTH-1:0]     acc_col4,
    output logic [ACC_WIDTH-1:0]     acc_sum
);

    //-------------------------------------------------------------------------
    // Extract each column from the cache row.
    // We assume that row_in packs 4 columns as follows:
    // { col4 (MSB), col3, col2, col1 (LSB) }
    // If your cache packs the data differently, change these assignments.
    //-------------------------------------------------------------------------
    logic [DATA_WIDTH-1:0] col1, col2, col3, col4;
    assign col1 = row_in[DATA_WIDTH-1:0];
    assign col2 = row_in[(2*DATA_WIDTH)-1:DATA_WIDTH];
    assign col3 = row_in[(3*DATA_WIDTH)-1:(2*DATA_WIDTH)];
    assign col4 = row_in[(4*DATA_WIDTH)-1:(3*DATA_WIDTH)];

    //-------------------------------------------------------------------------
    // Multiply and Accumulate Operation
    // For every clock cycle, the module multiplies r by each input stream:
    // - For the cache: col1, col2, col3, and col4.
    // - For the extra stream: sum_val.
    // The products are accumulated in five separate registers.
    //-------------------------------------------------------------------------
    always_ff @(posedge clk or posedge rst) begin
        if (rst) begin
            acc_col1 <= '0;
            acc_col2 <= '0;
            acc_col3 <= '0;
            acc_col4 <= '0;
            acc_sum  <= '0;
        end else begin
            acc_col1 <= acc_col1 + (r * col1);
            acc_col2 <= acc_col2 + (r * col2);
            acc_col3 <= acc_col3 + (r * col3);
            acc_col4 <= acc_col4 + (r * col4);
            acc_sum  <= acc_sum  + (r * sum_val);
        end
    end

endmodule

verilog/encryptor/mla_acc_tb.sv
`timescale 1ns/1ps

module tb_mla_accumulator;

  // Simulation parameters:
  localparam DATA_WIDTH = 12;
  localparam ACC_WIDTH  = 32;
  localparam NUM_STREAMS = 4; // Four cache columns
  
  // Inputs
  logic                     clk;
  logic                     rst;
  logic signed   [2:0]      r;       // 3-bit signed multiplier
  logic [NUM_STREAMS*DATA_WIDTH-1:0] row_in;   // Packed cache row: {col4, col3, col2, col1}
  logic [DATA_WIDTH-1:0]    sum_val; // Additional stream input
  
  // Outputs
  logic [ACC_WIDTH-1:0]     acc_col1;
  logic [ACC_WIDTH-1:0]     acc_col2;
  logic [ACC_WIDTH-1:0]     acc_col3;
  logic [ACC_WIDTH-1:0]     acc_col4;
  logic [ACC_WIDTH-1:0]     acc_sum;
  
  // Instantiate the DUT.
  mla_accumulator #(
    .DATA_WIDTH(DATA_WIDTH),
    .ACC_WIDTH(ACC_WIDTH)
  ) dut (
    .clk(clk),
    .rst(rst),
    .r(r),
    .row_in(row_in),
    .sum_val(sum_val),
    .acc_col1(acc_col1),
    .acc_col2(acc_col2),
    .acc_col3(acc_col3),
    .acc_col4(acc_col4),
    .acc_sum(acc_sum)
  );
  
  // Clock generation: 10 ns period.
  initial clk = 0;
  always #5 clk = ~clk;
  
  // Test stimulus.
  initial begin
    integer i;
    
    // Initialize the dump file for waveform viewing.
    $dumpfile("tb_mla_accumulator.vcd");
    $dumpvars(0, tb_mla_accumulator);
    
    // Initialize inputs.
    rst      = 1;
    r        = 0;
    row_in   = '0;
    sum_val  = '0;
    
    // Hold reset for a few cycles.
    #15;
    rst = 0;
    
    // First test phase: use positive r.
    // For 10 clock cycles, apply r = 3 and update row_in and sum_val.
    for (i = 0; i < 10; i = i + 1) begin
      @(posedge clk);
      // Set r (3-bit signed). Here r = 3.
      r = 3;
      // Construct row_in as {col4, col3, col2, col1}.
      // For example, col1 = i+1, col2 = i+2, col3 = i+3, col4 = i+4.
      row_in = { 12'(i+4), 12'(i+3), 12'(i+2), 12'(i+1) };
      // Set sum_val to i+5.
      sum_val = 12'(i+5);
      
      // Optionally display the stimulus and current accumulators.
      $display("[Cycle %0d] r=%0d, row_in=%h, sum_val=%h || acc_col1=%h, acc_col2=%h, acc_col3=%h, acc_col4=%h, acc_sum=%h",
               i, r, row_in, sum_val, acc_col1, acc_col2, acc_col3, acc_col4, acc_sum);
    end
    
    // Second test phase: use negative r.
    // For 5 clock cycles, set r = -2.
    for (i = 0; i < 5; i = i + 1) begin
      @(posedge clk);
      r = -2;
      // Change the row pattern for variety.
      row_in = { 12'(i+10), 12'(i+11), 12'(i+12), 12'(i+13) };
      sum_val = 12'(i+14);
      
      $display("[Cycle %0d] r=%0d, row_in=%h, sum_val=%h || acc_col1=%h, acc_col2=%h, acc_col3=%h, acc_col4=%h, acc_sum=%h",
               10+i, r, row_in, sum_val, acc_col1, acc_col2, acc_col3, acc_col4, acc_sum);
    end
    
    // Wait a few more cycles to capture the final accumulator values.
    #50;
    $display("Final values: acc_col1=%h, acc_col2=%h, acc_col3=%h, acc_col4=%h, acc_sum=%h",
             acc_col1, acc_col2, acc_col3, acc_col4, acc_sum);
    
    $finish;
  end

endmodule

verilog/encryptor/tb_mla_accumulator.vcd
$date
	Sun Apr 13 00:26:31 2025
$end
$version
	Icarus Verilog
$end
$timescale
	1ps
$end
$scope module tb_mla_accumulator $end
$var wire 32 ! acc_sum [31:0] $end
$var wire 32 " acc_col4 [31:0] $end
$var wire 32 # acc_col3 [31:0] $end
$var wire 32 $ acc_col2 [31:0] $end
$var wire 32 % acc_col1 [31:0] $end
$var parameter 32 & ACC_WIDTH $end
$var parameter 32 ' DATA_WIDTH $end
$var parameter 32 ( NUM_STREAMS $end
$var reg 1 ) clk $end
$var reg 3 * r [2:0] $end
$var reg 48 + row_in [47:0] $end
$var reg 1 , rst $end
$var reg 12 - sum_val [11:0] $end
$scope module dut $end
$var wire 1 ) clk $end
$var wire 3 . r [2:0] $end
$var wire 48 / row_in [47:0] $end
$var wire 1 , rst $end
$var wire 12 0 sum_val [11:0] $end
$var wire 12 1 col4 [11:0] $end
$var wire 12 2 col3 [11:0] $end
$var wire 12 3 col2 [11:0] $end
$var wire 12 4 col1 [11:0] $end
$var parameter 32 5 ACC_WIDTH $end
$var parameter 32 6 DATA_WIDTH $end
$var reg 32 7 acc_col1 [31:0] $end
$var reg 32 8 acc_col2 [31:0] $end
$var reg 32 9 acc_col3 [31:0] $end
$var reg 32 : acc_col4 [31:0] $end
$var reg 32 ; acc_sum [31:0] $end
$upscope $end
$scope begin $unm_blk_4 $end
$var integer 32 < i [31:0] $end
$upscope $end
$upscope $end
$enddefinitions $end
$comment Show the parameter values. $end
$dumpall
b1100 6
b100000 5
b100 (
b1100 '
b100000 &
$end
#0
$dumpvars
bx <
b0 ;
b0 :
b0 9
b0 8
b0 7
b0 4
b0 3
b0 2
b0 1
b0 0
b0 /
b0 .
b0 -
1,
b0 +
b0 *
0)
b0 %
b0 $
b0 #
b0 "
b0 !
$end
#5000
1)
#10000
0)
#15000
b1111 !
b1111 ;
b1 4
b10 3
b11 2
b100 1
b101 -
b101 0
b100000000000011000000000010000000000001 +
b100000000000011000000000010000000000001 /
b11 *
b11 .
1)
b1 <
0,
#20000
0)
#25000
b100001 !
b100001 ;
b1100 "
b1100 :
b1001 #
b1001 9
b110 $
b110 8
b11 %
b11 7
b10 4
b11 3
b100 2
b101 1
b10 <
b110 -
b110 0
b101000000000100000000000011000000000010 +
b101000000000100000000000011000000000010 /
1)
#30000
0)
#35000
b110110 !
b110110 ;
b11011 "
b11011 :
b10101 #
b10101 9
b1111 $
b1111 8
b1001 %
b1001 7
b11 4
b100 3
b101 2
b110 1
b11 <
b111 -
b111 0
b110000000000101000000000100000000000011 +
b110000000000101000000000100000000000011 /
1)
#40000
0)
#45000
b1001110 !
b1001110 ;
b101101 "
b101101 :
b100100 #
b100100 9
b11011 $
b11011 8
b10010 %
b10010 7
b100 4
b101 3
b110 2
b111 1
b100 <
b1000 -
b1000 0
b111000000000110000000000101000000000100 +
b111000000000110000000000101000000000100 /
1)
#50000
0)
#55000
b1101001 !
b1101001 ;
b1000010 "
b1000010 :
b110110 #
b110110 9
b101010 $
b101010 8
b11110 %
b11110 7
b101 4
b110 3
b111 2
b1000 1
b101 <
b1001 -
b1001 0
b1000000000000111000000000110000000000101 +
b1000000000000111000000000110000000000101 /
1)
#60000
0)
#65000
b10000111 !
b10000111 ;
b1011010 "
b1011010 :
b1001011 #
b1001011 9
b111100 $
b111100 8
b101101 %
b101101 7
b110 4
b111 3
b1000 2
b1001 1
b110 <
b1010 -
b1010 0
b1001000000001000000000000111000000000110 +
b1001000000001000000000000111000000000110 /
1)
#70000
0)
#75000
b10101000 !
b10101000 ;
b1110101 "
b1110101 :
b1100011 #
b1100011 9
b1010001 $
b1010001 8
b111111 %
b111111 7
b111 4
b1000 3
b1001 2
b1010 1
b111 <
b1011 -
b1011 0
b1010000000001001000000001000000000000111 +
b1010000000001001000000001000000000000111 /
1)
#80000
0)
#85000
b11001100 !
b11001100 ;
b10010011 "
b10010011 :
b1111110 #
b1111110 9
b1101001 $
b1101001 8
b1010100 %
b1010100 7
b1000 4
b1001 3
b1010 2
b1011 1
b1000 <
b1100 -
b1100 0
b1011000000001010000000001001000000001000 +
b1011000000001010000000001001000000001000 /
1)
#90000
0)
#95000
b11110011 !
b11110011 ;
b10110100 "
b10110100 :
b10011100 #
b10011100 9
b10000100 $
b10000100 8
b1101100 %
b1101100 7
b1001 4
b1010 3
b1011 2
b1100 1
b1001 <
b1101 -
b1101 0
b1100000000001011000000001010000000001001 +
b1100000000001011000000001010000000001001 /
1)
#100000
0)
#105000
b100011101 !
b100011101 ;
b11011000 "
b11011000 :
b10111101 #
b10111101 9
b10100010 $
b10100010 8
b10000111 %
b10000111 7
b1010 4
b1011 3
b1100 2
b1101 1
b0 <
b1110 -
b1110 0
b1101000000001100000000001011000000001010 +
b1101000000001100000000001011000000001010 /
1)
#110000
0)
#115000
b101110001 !
b101110001 ;
b100100110 "
b100100110 :
b100000101 #
b100000101 9
b11100100 $
b11100100 8
b11000011 %
b11000011 7
b1101 4
b1100 3
b1011 2
b1010 1
b1 <
b1010000000001011000000001100000000001101 +
b1010000000001011000000001100000000001101 /
b110 *
b110 .
1)
#120000
0)
#125000
b111001011 !
b111001011 ;
b101100010 "
b101100010 :
b101000111 #
b101000111 9
b100101100 $
b100101100 8
b100010001 %
b100010001 7
b1110 4
b1101 3
b1100 2
b1011 1
b10 <
b1111 -
b1111 0
b1011000000001100000000001101000000001110 +
b1011000000001100000000001101000000001110 /
1)
#130000
0)
#135000
b1000101011 !
b1000101011 ;
b110100100 "
b110100100 :
b110001111 #
b110001111 9
b101111010 $
b101111010 8
b101100101 %
b101100101 7
b1111 4
b1110 3
b1101 2
b1100 1
b11 <
b10000 -
b10000 0
b1100000000001101000000001110000000001111 +
b1100000000001101000000001110000000001111 /
1)
#140000
0)
#145000
b1010010001 !
b1010010001 ;
b111101100 "
b111101100 :
b111011101 #
b111011101 9
b111001110 $
b111001110 8
b110111111 %
b110111111 7
b10000 4
b1111 3
b1110 2
b1101 1
b100 <
b10001 -
b10001 0
b1101000000001110000000001111000000010000 +
b1101000000001110000000001111000000010000 /
1)
#150000
0)
#155000
b1011111101 !
b1011111101 ;
b1000111010 "
b1000111010 :
b1000110001 #
b1000110001 9
b1000101000 $
b1000101000 8
b1000011111 %
b1000011111 7
b10001 4
b10000 3
b1111 2
b1110 1
b101 <
b10010 -
b10010 0
b1110000000001111000000010000000000010001 +
b1110000000001111000000010000000000010001 /
1)
#160000
0)
#165000
b1101101001 !
b1101101001 ;
b1010001110 "
b1010001110 :
b1010001011 #
b1010001011 9
b1010001000 $
b1010001000 8
b1010000101 %
b1010000101 7
1)
#170000
0)
#175000
b1111010101 !
b1111010101 ;
b1011100010 "
b1011100010 :
b1011100101 #
b1011100101 9
b1011101000 $
b1011101000 8
b1011101011 %
b1011101011 7
1)
#180000
0)
#185000
b10001000001 !
b10001000001 ;
b1100110110 "
b1100110110 :
b1100111111 #
b1100111111 9
b1101001000 $
b1101001000 8
b1101010001 %
b1101010001 7
1)
#190000
0)
#195000
b10010101101 !
b10010101101 ;
b1110001010 "
b1110001010 :
b1110011001 #
b1110011001 9
b1110101000 $
b1110101000 8
b1110110111 %
b1110110111 7
1)
#200000
0)
#205000
b10100011001 !
b10100011001 ;
b1111011110 "
b1111011110 :
b1111110011 #
b1111110011 9
b10000001000 $
b10000001000 8
b10000011101 %
b10000011101 7
1)
